odoo9_addon_base_view_inheritance_extension-9.0.1.1.0-py2.7-nspkg.pth
odoo_addons/base_view_inheritance_extension/__openerp__.py
odoo_addons/base_view_inheritance_extension/__init__.py
odoo_addons/base_view_inheritance_extension/README.rst
odoo_addons/base_view_inheritance_extension/models/ir_ui_view.py
odoo_addons/base_view_inheritance_extension/models/__init__.py
odoo_addons/base_view_inheritance_extension/i18n/tr.po
odoo_addons/base_view_inheritance_extension/i18n/sl.po
odoo_addons/base_view_inheritance_extension/i18n/de.po
odoo_addons/base_view_inheritance_extension/tests/test_base_view_inheritance_extension.py
odoo_addons/base_view_inheritance_extension/tests/__init__.py
odoo_addons/base_view_inheritance_extension/demo/ir_ui_view.xml
odoo_addons/base_view_inheritance_extension/static/description/icon.png
odoo9_addon_base_view_inheritance_extension-9.0.1.1.0.dist-info/top_level.txt
odoo9_addon_base_view_inheritance_extension-9.0.1.1.0.dist-info/WHEEL
odoo9_addon_base_view_inheritance_extension-9.0.1.1.0.dist-info/RECORD
odoo9_addon_base_view_inheritance_extension-9.0.1.1.0.dist-info/metadata.json
odoo9_addon_base_view_inheritance_extension-9.0.1.1.0.dist-info/DESCRIPTION.rst
odoo9_addon_base_view_inheritance_extension-9.0.1.1.0.dist-info/METADATA
odoo9_addon_base_view_inheritance_extension-9.0.1.1.0.dist-info/namespace_packages.txt
